graphby/__init__.py
graphby/graphby.py
graphby/version.py
graphby-0.0.3.dist-info/LICENSE
graphby-0.0.3.dist-info/METADATA
graphby-0.0.3.dist-info/WHEEL
graphby-0.0.3.dist-info/top_level.txt
graphby-0.0.3.dist-info/RECORD
