Metadata-Version: 2.1
Name: graphby
Version: 0.0.3
Summary: Generate simple visualizations on terminal.
Home-page: https://github.com/rmaniego/graphby
Author: Rodney Maniego Jr.
Author-email: rod.maniego23@gmail.com
License: MIT
Download-URL: https://github.com/rmaniego/graphby/archive/v1.0.tar.gz
Keywords: CLI,Graph,Visualization
Platform: UNKNOWN
Classifier: Development Status :: 5 - Production/Stable
Classifier: Intended Audience :: Developers
Classifier: Topic :: Software Development :: Build Tools
Classifier: License :: OSI Approved :: MIT License
Classifier: Programming Language :: Python :: 3
Requires-Python: >=3.6
